Py2Tikz/__init__.py
Py2Tikz/py2tikz.py
tests/__init__.py
tests/test.py
Py2Tikz-0.0.2.dist-info/LICENSE
Py2Tikz-0.0.2.dist-info/METADATA
Py2Tikz-0.0.2.dist-info/WHEEL
Py2Tikz-0.0.2.dist-info/top_level.txt
Py2Tikz-0.0.2.dist-info/RECORD
