Metadata-Version: 2.1
Name: Py2Tikz
Version: 0.0.2
Summary: A Python library for generating LaTeX pgfplots/tikz code.
Home-page: https://github.com/patrikdennis/Py2Tikz
Author: Patrik Franzén
Author-email: patrik.franzen.dennis@gmail.com
Classifier: Programming Language :: Python :: 3
Classifier: License :: OSI Approved :: MIT License
Classifier: Operating System :: OS Independent
Requires-Python: >=3.6
License-File: LICENSE
Requires-Dist: numpy
Requires-Dist: pandas
